[
{"title":"桌面天气 v0.1.3","url":"works/16.05.30_22:08:12.html","icon":"works/16.05.30_22:08:12/tianqi.png","made":"16.05.30_22:08:12","update":"16.06.10_13:26:07"},
{"title":"epub阅读器 v0.3","url":"works/16.06.01_22:17:06.html","icon":"works/16.06.01_22:17:06/book.png","made":"16.06.01_22:17:06","update":"16.06.10_14:08:02"},
{"title":"创建快捷方式 v0.2","url":"works/16.06.10_02:05:59.html","icon":"works/16.06.10_02:05:59/mkdesktop.png","made":"16.06.10_02:05:59","update":"16.06.10_14:05:27"},
{"title":"[定时提醒 桌面便签] NoteWei  v0.3","url":"works/16.09.12_20:05:17.html","icon":"works/16.09.12_20:05:17/wei2.png","made":"16.09.12_20:05:17","update":"17.04.11_20:13:20"},
{"title":"内存网速监测-悬浮版 v0.5.1","url":"works/17.02.05_00:29:05.html","icon":"works/17.02.05_00:29:05/watch.png","made":"17.02.05_00:29:05","update":"17.03.21_22:11:53"},
{"title":"其他制作/打包/分享","url":"works/17.04.12_23:54:50.html","icon":"works/17.04.12_23:54:50/timg (1).jpg","made":"17.04.12_23:54:50","update":"17.04.12_23:54:50"},
{"title":"网页云音乐","url":"works/17.12.20_22:47:12.html","icon":"works/17.12.20_22:47:12/webmusic.png","made":"17.12.20_22:47:12","update":"17.12.20_22:52:48"}
]